CHANGES.txt
MANIFEST.in
README.md
setup.py
pyraml/__init__.py
pyraml/constants.py
pyraml/entities.py
pyraml/fields.py
pyraml/model.py
pyraml/parser.py
pyraml/raml_elements.py
pyraml_parser.egg-info/PKG-INFO
pyraml_parser.egg-info/SOURCES.txt
pyraml_parser.egg-info/dependency_links.txt
pyraml_parser.egg-info/pbr.json
pyraml_parser.egg-info/requires.txt
pyraml_parser.egg-info/top_level.txt
pyraml_parser.egg-info/zip-safe