Metadata-Version: 1.1
Name: pyraml-parser
Version: 0.1.9
Summary: Python parser for RAML.
Home-page: https://github.com/an2deg/pyraml-parser
Author: Andrii Degtiarov
Author-email: andrew.degtiariov@gmail.com
License: MIT
Platform: UNKNOWN
Classifier: Development Status :: 4 - Beta
Classifier: Environment :: Console
Classifier: Intended Audience :: Developers
Classifier: License :: OSI Approved :: MIT License
Classifier: Programming Language :: Python
Classifier: Programming Language :: Python :: 2
Classifier: Programming Language :: Python :: 2.7
Classifier: Programming Language :: Python :: 3
Classifier: Programming Language :: Python :: 3.6
Classifier: Programming Language :: Python :: 3.7
Classifier: Topic :: Software Development :: Libraries
